astro_identity_and_access_management_iam_api_client/__init__.py
astro_identity_and_access_management_iam_api_client/api/__init__.py
astro_identity_and_access_management_iam_api_client/api/agent_token/__init__.py
astro_identity_and_access_management_iam_api_client/api/agent_token/create_agent_token.py
astro_identity_and_access_management_iam_api_client/api/agent_token/delete_agent_token.py
astro_identity_and_access_management_iam_api_client/api/agent_token/get_agent_token.py
astro_identity_and_access_management_iam_api_client/api/agent_token/list_agent_tokens.py
astro_identity_and_access_management_iam_api_client/api/allowed_ip_address_range/__init__.py
astro_identity_and_access_management_iam_api_client/api/allowed_ip_address_range/create_allowed_ip_address_range.py
astro_identity_and_access_management_iam_api_client/api/allowed_ip_address_range/delete_allowed_ip_address_range.py
astro_identity_and_access_management_iam_api_client/api/allowed_ip_address_range/list_allowed_ip_address_ranges.py
astro_identity_and_access_management_iam_api_client/api/api_token/__init__.py
astro_identity_and_access_management_iam_api_client/api/api_token/create_api_token.py
astro_identity_and_access_management_iam_api_client/api/api_token/delete_api_token.py
astro_identity_and_access_management_iam_api_client/api/api_token/get_api_token.py
astro_identity_and_access_management_iam_api_client/api/api_token/list_api_tokens.py
astro_identity_and_access_management_iam_api_client/api/api_token/rotate_api_token.py
astro_identity_and_access_management_iam_api_client/api/api_token/update_api_token.py
astro_identity_and_access_management_iam_api_client/api/api_token/update_api_token_roles.py
astro_identity_and_access_management_iam_api_client/api/authorization/__init__.py
astro_identity_and_access_management_iam_api_client/api/authorization/list_permission_groups.py
astro_identity_and_access_management_iam_api_client/api/invite/__init__.py
astro_iam_api-1.1.1.dist-info/METADATA
astro_iam_api-1.1.1.dist-info/WHEEL
astro_iam_api-1.1.1.dist-info/RECORD
